dasende/__init__.py
dasende/core.py
dasende-0.1.0.dist-info/licenses/LICENSE
dasende-0.1.0.dist-info/METADATA
dasende-0.1.0.dist-info/WHEEL
dasende-0.1.0.dist-info/top_level.txt
dasende-0.1.0.dist-info/RECORD
